{
  "state": {
    "dataset_info": {
      "downscale_factor": 4,
      "color_space": "srgb",
      "type": "forward-facing",
      "evaluation_protocol": "nerf",
      "expected_scene_scale": 0.5,
      "id": "llff",
      "scene": "fortress",
      "name": "LLFF",
      "metrics": [
        {
          "id": "psnr",
          "name": "PSNR",
          "description": "Peak Signal to Noise Ratio. The higher the better.",
          "ascending": true,
          "link": "https://en.wikipedia.org/wiki/Peak_signal-to-noise_ratio"
        },
        {
          "id": "ssim",
          "name": "SSIM",
          "description": "Structural Similarity Index. The higher the better. The implementation matches JAX's SSIM and torchmetrics's SSIM (with default parameters).",
          "ascending": true,
          "link": "https://en.wikipedia.org/wiki/Structural_similarity"
        },
        {
          "id": "lpips_vgg",
          "name": "LPIPS (VGG)",
          "description": "Learned Perceptual Image Patch Similarity. The lower the better. The implementation uses VGG backbone and matches lpips pip package with checkpoint version 0.1",
          "ascending": false,
          "link": "https://richzhang.github.io/PerceptualSimilarity/"
        }
      ],
      "default_metric": "psnr",
      "description": "LLFF is a dataset of forward-facing scenes with a small variation in camera pose. NeRF methods usually use NDC-space parametrization for the scene representation.",
      "link": "https://bmild.github.io/llff/",
      "paper_link": "https://arxiv.org/pdf/1905.00889.pdf",
      "paper_authors": [
        "Ben Mildenhall",
        "Pratul P. Srinivasan",
        "Rodrigo Ortiz-Cayon",
        "Nima Khademi Kalantari",
        "Ravi Ramamoorthi",
        "Ren Ng",
        "Abhishek Kar"
      ],
      "paper_title": "LLFF: A Large-Scale, Long-Form Video Dataset for 3D Scene Understanding",
      "scenes": [
        {
          "id": "fern",
          "name": "Fern"
        },
        {
          "id": "flower",
          "name": "Flower"
        },
        {
          "id": "fortress",
          "name": "Fortress"
        },
        {
          "id": "horns",
          "name": "Horns"
        },
        {
          "id": "leaves",
          "name": "Leaves"
        },
        {
          "id": "orchids",
          "name": "Orchids"
        },
        {
          "id": "room",
          "name": "Room"
        },
        {
          "id": "trex",
          "name": "Trex"
        }
      ]
    }
  },
  "viewer_transform": [
    0.17685283010104094,
    -0.0018408291226848878,
    -0.00041142410874889435,
    -0.041888288815729605,
    0.0004087625705314516,
    -0.0002578008515448752,
    0.17686222855173378,
    -0.008318172941227563,
    -0.0018414219552066707,
    -0.17685312076202064,
    -0.00025353169597689475,
    -0.010451324946433811
  ],
  "viewer_initial_pose": [
    0.9992723961365481,
    -0.007786107605142932,
    -0.03733704390927061,
    -0.1862082256480749,
    0.03641723815315763,
    -0.09613234914163626,
    0.9947021444702967,
    0.18973940617005453,
    -0.011334155672914768,
    -0.9953381073669749,
    -0.0957788543380555,
    0.5187506681366943
  ],
  "dataset": {
    "url": "https://huggingface.co/datasets/nerfbaselines/nerfbaselines-data/resolve/main/llff/fortress-nbv.json"
  }
}